rebin.py
rebin-1.0.1.dist-info/DESCRIPTION.rst
rebin-1.0.1.dist-info/METADATA
rebin-1.0.1.dist-info/RECORD
rebin-1.0.1.dist-info/WHEEL
rebin-1.0.1.dist-info/metadata.json
rebin-1.0.1.dist-info/top_level.txt
