Metadata-Version: 2.0
Name: rebin
Version: 1.0.1
Summary: Python/NumPy implementation of IDL's rebin function.
Home-page: https://github.com/sbrisard/rebin
Author: Sebastien Brisard
Author-email: UNKNOWN
License: BSD-3
Platform: UNKNOWN
Classifier: Development Status :: 4 - Beta
Classifier: Intended Audience :: Developers
Classifier: Intended Audience :: Science/Research
Classifier: License :: OSI Approved :: BSD License
Classifier: Operating System :: OS Independent
Classifier: Topic :: Software Development :: Build Tools
Classifier: Programming Language :: Python :: 2.7
Classifier: Programming Language :: Python :: 3
Classifier: Topic :: Scientific/Engineering
Requires-Dist: numpy
